pigi/__init__.py
pigi/pigic.py
pigi-0.0.7.dist-info/LICENSE.txt
pigi-0.0.7.dist-info/METADATA
pigi-0.0.7.dist-info/WHEEL
pigi-0.0.7.dist-info/top_level.txt
pigi-0.0.7.dist-info/RECORD
